dist
mypy_boto3_accessanalyzer
mypy_boto3_account
mypy_boto3_acm
mypy_boto3_acm_pca
mypy_boto3_aiops
mypy_boto3_amp
mypy_boto3_amplify
mypy_boto3_amplifybackend
mypy_boto3_amplifyuibuilder
mypy_boto3_apigateway
mypy_boto3_apigatewaymanagementapi
mypy_boto3_apigatewayv2
mypy_boto3_appconfig
mypy_boto3_appconfigdata
mypy_boto3_appfabric
mypy_boto3_appflow
mypy_boto3_appintegrations
mypy_boto3_application_autoscaling
mypy_boto3_application_insights
mypy_boto3_application_signals
mypy_boto3_applicationcostprofiler
mypy_boto3_appmesh
mypy_boto3_apprunner
mypy_boto3_appstream
mypy_boto3_appsync
mypy_boto3_arc_region_switch
mypy_boto3_arc_zonal_shift
mypy_boto3_artifact
mypy_boto3_athena
mypy_boto3_auditmanager
mypy_boto3_autoscaling
mypy_boto3_autoscaling_plans
mypy_boto3_b2bi
mypy_boto3_backup
mypy_boto3_backup_gateway
mypy_boto3_backupsearch
mypy_boto3_batch
mypy_boto3_bcm_dashboards
mypy_boto3_bcm_data_exports
mypy_boto3_bcm_pricing_calculator
mypy_boto3_bcm_recommended_actions
mypy_boto3_bedrock
mypy_boto3_bedrock_agent
mypy_boto3_bedrock_agent_runtime
mypy_boto3_bedrock_agentcore
mypy_boto3_bedrock_agentcore_control
mypy_boto3_bedrock_data_automation
mypy_boto3_bedrock_data_automation_runtime
mypy_boto3_bedrock_runtime
mypy_boto3_billing
mypy_boto3_billingconductor
mypy_boto3_braket
mypy_boto3_budgets
mypy_boto3_ce
mypy_boto3_chatbot
mypy_boto3_chime
mypy_boto3_chime_sdk_identity
mypy_boto3_chime_sdk_media_pipelines
mypy_boto3_chime_sdk_meetings
mypy_boto3_chime_sdk_messaging
mypy_boto3_chime_sdk_voice
mypy_boto3_cleanrooms
mypy_boto3_cleanroomsml
mypy_boto3_cloud9
mypy_boto3_cloudcontrol
mypy_boto3_clouddirectory
mypy_boto3_cloudformation
mypy_boto3_cloudfront
mypy_boto3_cloudfront_keyvaluestore
mypy_boto3_cloudhsm
mypy_boto3_cloudhsmv2
mypy_boto3_cloudsearch
mypy_boto3_cloudsearchdomain
mypy_boto3_cloudtrail
mypy_boto3_cloudtrail_data
mypy_boto3_cloudwatch
mypy_boto3_codeartifact
mypy_boto3_codebuild
mypy_boto3_codecatalyst
mypy_boto3_codecommit
